Workbook

Sheet Summary
A1: Roomly: Production Readiness
A2: Audit date: 2026-10-10. Edit Status / Owner / Target date on the Issues sheet; counts below update automatically.
A4: Severity | B4: Meaning | C4: Total | D4: Open | E4: In progress | F4: Done | G4: % done
A5: Blocker | B5: Store rejection, security hole or data loss. Must fix before launch. | C5: =COUNTIF(Issues!$B:$B,A5) | D5: =COUNTIFS(Issues!$B:$B,A5,Issues!$J:$J,"Open") | E5: =COUNTIFS(Issues!$B:$B,A5,Issues!$J:$J,"In progress") | F5: =COUNTIFS(Issues!$B:$B,A5,Issues!$J:$J,"Done") | G5: =IF(C5=0,0,F5/C5)
A6: High | B6: Fix before launch or it breaks as you grow. | C6: =COUNTIF(Issues!$B:$B,A6) | D6: =COUNTIFS(Issues!$B:$B,A6,Issues!$J:$J,"Open") | E6: =COUNTIFS(Issues!$B:$B,A6,Issues!$J:$J,"In progress") | F6: =COUNTIFS(Issues!$B:$B,A6,Issues!$J:$J,"Done") | G6: =IF(C6=0,0,F6/C6)
A7: Medium | B7: Needed for a multi-country, large-scale product. | C7: =COUNTIF(Issues!$B:$B,A7) | D7: =COUNTIFS(Issues!$B:$B,A7,Issues!$J:$J,"Open") | E7: =COUNTIFS(Issues!$B:$B,A7,Issues!$J:$J,"In progress") | F7: =COUNTIFS(Issues!$B:$B,A7,Issues!$J:$J,"Done") | G7: =IF(C7=0,0,F7/C7)
A8: Low | B8: Cleanup. | C8: =COUNTIF(Issues!$B:$B,A8) | D8: =COUNTIFS(Issues!$B:$B,A8,Issues!$J:$J,"Open") | E8: =COUNTIFS(Issues!$B:$B,A8,Issues!$J:$J,"In progress") | F8: =COUNTIFS(Issues!$B:$B,A8,Issues!$J:$J,"Done") | G8: =IF(C8=0,0,F8/C8)
A9: Total | C9: =SUM(C5:C8) | D9: =SUM(D5:D8) | E9: =SUM(E5:E8) | F9: =SUM(F5:F8) | G9: =IF(C9=0,0,F9/C9)
A11: Suggested order
A12: 1. Security fix: B1 (about a day).
A13: 2. Store blockers: B2-B11. Start the 14-day Google Play closed test now so it runs in parallel.
A14: 3. Scale: H1-H5, H7, H9 (balance snapshots, pagination, indexes, push worker, pg_cron, staging + Supabase CLI).
A15: 4. Growth: Medium items, depending on launch markets.
A17: Effort key: S = under 1 day, M = 1-3 days, L = 1+ week (rough estimates).

Sheet Issues
A1: ID | B1: Severity | C1: Category | D1: Issue | E1: Details | F1: Location | G1: Impact | H1: Recommended fix | I1: Effort | J1: Status | K1: Owner | L1: Target date | M1: Notes
A2: B1 | B2: Blocker | C2: Security | D2: Notification functions callable by any client | E2: notify_household and send_push_for_notification were created after the 'revoke execute from anon' in 0004 and never had permissions locked down; Postgres grants EXECUTE to PUBLIC by default. ensure_period also lacks a household membership check. | F2: supabase/migrations/0016_push.sql:108-191; 0011_apply_fixes.sql:24 | G2: Anyone with the public key and a household ID can insert fake notifications and push arbitrary text to every phone in that household; signed-in users can create period rows in other households. | H2: Revoke EXECUTE on all functions from public/anon/authenticated, grant back only RPCs the app calls; ALTER DEFAULT PRIVILEGES so new functions start closed; add membership check to ensure_period. | I2: S | J2: Open
A3: B2 | B3: Blocker | C3: Store compliance | D3: No in-app account deletion | E3: Settings only has Export and Sign out. No delete-account RPC or Edge Function; remove_member is owner-removes-member, not self-deletion. | F3: src/app/(app)/settings.tsx; account-edit.tsx | G3: Automatic rejection: Apple guideline 5.1.1(v) and Google Play account deletion policy. | H3: Add Delete Account screen + Edge Function (service role) that deletes auth.users row and scrubs/anonymises personal data; add web URL for Play's deletion form. | I3: M | J3: Open
A4: B3 | B4: Blocker | C4: Legal / Store compliance | D4: No privacy policy, terms or support URL | E4: No privacy/terms links anywhere in the app; no consent text on register. No hosted policy page. | F4: src/app/register.tsx; settings.tsx | G4: Both stores require a privacy policy URL; Apple requires a support URL. Data Safety form (Play) and App Privacy labels (Apple) must be filled. | H4: Host privacy policy, terms, support page; link from register and Account; complete Data Safety and App Privacy questionnaires. | I4: S | J4: Open
A5: B4 | B5: Blocker | C5: Branding / Store | D5: App icon is the Expo template logo | E5: assets/images/icon.png and assets/expo.icon are stock Expo; adaptive icon background is template default; display name is lowercase 'roomly'. | F5: assets/images/icon.png; assets/expo.icon; app.json | G5: Rejection or app looks like a test build. | H5: Design real icon set (1024 iOS, adaptive Android fg/bg/monochrome), splash; set name to 'Roomly'. | I5: S | J5: Open
A6: B5 | B6: Blocker | C6: Build / Release | D6: EAS cloud builds crash on launch (no env vars) | E6: EXPO_PUBLIC_SUPABASE_* exist only in local .env (gitignored); eas.json has no env; supabase.ts throws if missing. | F6: eas.json; src/lib/supabase.ts:10 | G6: Every cloud build crashes on start. | H6: Create EAS environment variables per environment (development/preview/production). | I6: S | J6: Done | M6: EAS production env vars set and verified 2026-10-10. Add to preview env before preview builds.
A7: B6 | B7: Blocker | C7: Store compliance (iOS) | D7: Missing iOS privacy manifest | E7: No ios.privacyManifests in app.json. AsyncStorage, SQLite and file system use Apple 'required reason' APIs. | F7: app.json | G7: App Store upload flagged/rejected. | H7: Add ios.privacyManifests with NSPrivacyAccessedAPITypes (UserDefaults, FileTimestamp, etc.) and collected data types. | I7: S | J7: Open
A8: B7 | B8: Blocker | C8: Infrastructure | D8: Supabase built-in email limits | E8: Default Supabase SMTP sends only a few emails per hour and is not meant for production. | F8: Supabase dashboard > Auth > SMTP | G8: Sign-up confirmations and password resets silently fail once real users arrive. | H8: Configure custom SMTP (Resend, AWS SES, Postmark) with SPF/DKIM on your domain; brand email templates. | I8: S | J8: Open
A9: B8 | B9: Blocker | C9: Infrastructure | D9: Supabase plan / backups | E9: Free projects pause after inactivity and have no point-in-time recovery. Only backup today is in-app CSV export. | F9: Supabase project | G9: Downtime and unrecoverable loss of a financial ledger. | H9: Move to Pro plan, enable PITR, and run a test restore on a schedule. | I9: S | J9: Open
A10: B9 | B10: Blocker | C10: Observability | D10: No crash reporting and no error boundaries | E10: No Sentry/Bugsnag; no ErrorBoundary export in any layout; only two __DEV__ console.warn calls. | F10: src/app/_layout.tsx; package.json | G10: A single render error closes the app and you never find out. | H10: Add Sentry (@sentry/react-native) with source maps uploaded from EAS; root + per-route ErrorBoundary. | I10: S | J10: Open
A11: B10 | B11: Blocker | C11: Store process (Android) | D11: Google Play closed-testing requirement | E11: New personal developer accounts must run a closed test with 12+ testers for 14 consecutive days before production access. | F11: Play Console | G11: Cannot publish publicly until the test is complete. | H11: Start the closed test now, in parallel with other fixes. | I11: S | J11: Open
A12: B11 | B12: Blocker | C12: Store process (iOS) | D12: App Review demo account | E12: Every screen requires sign-in and a household. | F12: App Store Connect | G12: Reviewer cannot use the app, so it is rejected. | H12: Provide a ready demo account with seeded household data and a second member; keep it alive. | I12: S | J12: Open
A13: H1 | B13: High | C13: Scalability | D13: Balances recompute from full history on every read | E13: member_balances / member_ledger re-add a household's entire history every time; no snapshot for closed months. | F13: supabase/migrations/0024_one_balance_expression.sql:61-153 | G13: Each household gets slower every month; DB CPU grows with total data. | H13: Store a balance snapshot per closed period and sum only open months on top. | I13: M | J13: Open
A14: H2 | B14: High | C14: Scalability / UX | D14: No pagination | E14: History loads fixed 200, search loads 500 and filters on device; settlements and pairwise screens load everything. Older history unreachable. | F14: history.tsx:30; search.tsx:18; queries.ts:599,1052 | G14: Slow screens, high data usage, missing history for long-lived households. | H14: Cursor pagination with useInfiniteQuery + .range(); server-side search (trigram/FTS). | I14: M | J14: Open
A15: H3 | B15: High | C15: Performance | D15: Every live update refetches every query | E15: Realtime handler and sync call invalidateQueries() with no filter. | F15: src/lib/realtime.ts:74; src/lib/sync.tsx | G15: Each change makes every open device refetch everything; DB load multiplies with users. | H15: Invalidate only affected query keys based on event kind. | I15: S | J15: Open
A16: H4 | B16: High | C16: Database | D16: Missing indexes | E16: No index on settlements(from_member), (to_member), (period_id); notification_reads(member_id); audit_log(household_id, created_at); push_tokens(token); pending_changes, join_requests, invites; several unindexed FKs. | F16: supabase/migrations | G16: Full table scans on hot paths as data grows. | H16: Add migration with indexes; wrap RLS helper calls as (select current_household()). | I16: S | J16: Open
A17: H5 | B17: High | C17: Push notifications | D17: Push is fire-and-forget | E17: Single net.http_post from trigger; errors swallowed; no retry; no 100-message chunking; DeviceNotRegistered tokens never cleaned; rupee sign hardcoded. | F17: supabase/migrations/0016_push.sql:150 | G17: Lost notifications, invisible failures, growing dead-token list. | H17: Queue table + worker (pg_cron or Edge Function) with batching, retries, receipt checks and token cleanup. | I17: M | J17: Open
A18: H6 | B18: High | C18: Push / Privacy | D18: Sign-out does not unregister push token | E18: unregister_push_token RPC exists but nothing calls it. | F18: src/lib/session.tsx:313 | G18: Signed-out phone keeps receiving the household's notifications. | H18: Call unregister_push_token before signOut. | I18: S | J18: Open
... A43: L6 | B43: Low | C43: UX copy | D43: Developer text visible to users | E43: Message says 'See PUSH-SETUP.md'. | F43: src/lib/push.ts:110 | G43: Unprofessional. | H43: Replace with user-friendly copy. | I43: S | J43: Open

Sheet What We Have
A1: Area | B1: What exists | C1: State
A2: Authentication | B2: Email/password sign-up, email confirmation, password reset (PKCE), session auto-refresh | C2: Working
A3: Households | B3: Create, invite codes, join approval, ownership handover, away periods, member admin | C3: Working
A4: Expenses | B4: Equal/custom splits, categories, edit history, void/undo, search | C4: Working
A5: Recurring expenses | B5: Idempotent posting, missed-month backfill (12 months), day 1-31 | C5: Working
A6: Settlements | B6: Pairwise balances, suggested payments, payee confirms payment | C6: Working
A7: Monthly close | B7: Closed months locked, enforced in DB | C7: Working
A8: Reports | B8: Charts by category and member, month statements | C8: Working
A9: Export / backup | B9: CSV export via share sheet | C9: Working
A10: Offline | B10: Durable outbox for new expenses with idempotent server writes; persisted query cache (7 days) | C10: Working (partial)
A11: Notifications | B11: In-app feed with unread badge, live updates via Supabase Realtime | C11: Working
A12: Push | B12: Token registration, Android channel, server send via pg_net | C12: Working (needs hardening)
... A19: Code hygiene | B19: No console.log, no TODO/FIXME | C19: Clean

Sheet Not In App
A1: Area | B1: Feature | C1: Notes | D1: Decision
A2: Monetization | B2: Subscriptions / in-app purchases (RevenueCat) | C2: Decide business model before launch | D2: Undecided
A3: Social sign-in | B3: Google and Apple sign-in | C3: If Google is added, Sign in with Apple becomes mandatory on iOS | D3: Undecided
A4: Receipts | B4: Receipt photo capture and storage | C4: Needs camera/photos permission strings and Storage bucket with RLS | D4: Undecided
A5: Payments | B5: UPI / payment app deep links to settle | C5: Common expectation in India | D5: Undecided
A6: Multi-currency | B6: Multiple currencies within one household, FX | C6: Ties to M1 | D6: Undecided
A7: Tablet | B7: iPad / Android tablet layouts | C7: supportsTablet is false | D7: Undecided
A8: Widgets | B8: Home-screen widgets (balance at a glance) | C8: Optional growth feature | D8: Undecided
A9: Admin console | B9: Internal support/admin tool | C9: Needed to help users at scale | D9: Undecided
A10: Moderation | B10: Abuse reporting, block, account lock | C10: Needed with open sign-up | D10: Undecided
A11: Monitoring | B11: Uptime, DB metrics, alerting (e.g. on ledger_imbalance) | C11: Operational must-have | D11: Undecided
A12: Legal | B12: India DPDP Act 2023 compliance; GDPR if EU users | C12: Consent, data requests, grievance officer | D12: Undecided
A13: Store assets | B13: Screenshots, descriptions, feature graphic, keywords | C13: Required for listings | D13: Undecided

Sheet Legend
A1: How to use
A3: Light-yellow cells are for you to edit: Status, Owner, Target date, Notes (Issues) and Decision (Not In App).
A4: Status options: Open, In progress, Done, Won't fix. Done rows turn green and struck through.
A5: Summary counts and % done are formulas driven by the Issues sheet.
A6: Severity: Blocker = store rejection / security / data loss; High = breaks at scale; Medium = needed for growth; Low = cleanup.
A7: Effort: S < 1 day, M 1-3 days, L 1+ week. Rough estimates from the 2026-10-10 code audit.
A8: Locations are paths in the roomly repo, with line numbers where known.
